LICENSE
MANIFEST.in
README.rst
setup.cfg
setup.py
django_ip_guard/__init__.py
django_ip_guard/admin.py
django_ip_guard/apps.py
django_ip_guard/middleware.py
django_ip_guard/models.py
django_ip_guard/utils.py
django_ip_guard.egg-info/PKG-INFO
django_ip_guard.egg-info/SOURCES.txt
django_ip_guard.egg-info/dependency_links.txt
django_ip_guard.egg-info/requires.txt
django_ip_guard.egg-info/top_level.txt
django_ip_guard/migrations/0001_initial.py
django_ip_guard/migrations/__init__.py
docs/README.rst