Metadata-Version: 1.2
Name: django-ip-guard
Version: 1.1
Summary: A Django app to protect your django website from spammers, bots and bad peoples by their IP addresses.
Home-page: UNKNOWN
Author: Md Rakibul Hasan
License: MIT License
Platform: UNKNOWN
Requires-Python: <4.0,>=3.6
